cspreports/__init__.py
cspreports/admin.py
cspreports/apps.py
cspreports/conf.py
cspreports/filters.py
cspreports/models.py
cspreports/summary.py
cspreports/urls.py
cspreports/utils.py
cspreports/views.py
cspreports/management/__init__.py
cspreports/management/commands/__init__.py
cspreports/management/commands/clean_cspreports.py
cspreports/management/commands/make_csp_summary.py
cspreports/migrations/0001_initial.py
cspreports/migrations/0002_auto_20141011_1800.py
cspreports/migrations/0003_report_fields.py
cspreports/migrations/0004_cspreport_user_agent.py
cspreports/migrations/__init__.py
cspreports/templates/cspreports/summary.txt
cspreports/tests/__init__.py
cspreports/tests/models.py
cspreports/tests/settings.py
cspreports/tests/test_commands.py
cspreports/tests/test_custom_model.py
cspreports/tests/test_models.py
cspreports/tests/test_summary.py
cspreports/tests/test_urls.py
cspreports/tests/test_utils.py
cspreports/tests/utils.py
django_csp_reports-1.10.0.dist-info/LICENSE
django_csp_reports-1.10.0.dist-info/METADATA
django_csp_reports-1.10.0.dist-info/WHEEL
django_csp_reports-1.10.0.dist-info/top_level.txt
django_csp_reports-1.10.0.dist-info/RECORD
