Metadata-Version: 2.1
Name: django-csp-reports
Version: 1.10.0
Summary: A Django app for handling reports from web browsers of violations of your website's HTTP Content Security Policy.
Home-page: https://github.com/adamalton/django-csp-reports
Author: Adam Alton
Author-email: adamalton@gmail.com
Keywords: django,csp,content security policy
Classifier: License :: OSI Approved :: MIT License
Classifier: Framework :: Django
Classifier: Programming Language :: Python
Classifier: Programming Language :: Python :: 3
Classifier: Programming Language :: Python :: 3 :: Only
Classifier: Programming Language :: Python :: 3.8
Classifier: Programming Language :: Python :: 3.9
Classifier: Programming Language :: Python :: 3.10
Classifier: Programming Language :: Python :: 3.11
Classifier: Programming Language :: Python :: 3.12
Classifier: Programming Language :: Python :: 3.13
Requires-Python: >=3.8
License-File: LICENSE
Requires-Dist: django<5.3,>=3.2
Provides-Extra: quality
Requires-Dist: isort; extra == "quality"
Requires-Dist: flake8; extra == "quality"
Provides-Extra: test
Requires-Dist: coverage; extra == "test"
